{"match_id":4887481193,"barracks_status_dire":63,"barracks_status_radiant":63,"chat":null,"cluster":136,"cosmetics":null,"dire_score":0,"dire_team_id":null,"draft_timings":null,"duration":2014,"engine":1,"first_blood_time":1989,"game_mode":21,"human_players":2,"leagueid":0,"lobby_type":8,"match_seq_num":4102520546,"negative_votes":0,"objectives":null,"picks_bans":null,"positive_votes":0,"radiant_gold_adv":null,"radiant_score":1,"radiant_team_id":null,"radiant_win":true,"radiant_xp_adv":null,"skill":null,"start_time":1562417131,"teamfights":null,"tower_status_dire":2039,"tower_status_radiant":2047,"version":null,"replay_salt":1903585295,"series_id":0,"series_type":0,"players":[{"match_id":4887481193,"player_slot":0,"ability_targets":null,"ability_upgrades_arr":[6344,7307,6344,7307,6344,6343,6344,7307,7307,6160,6461,6343,6461,6461,9135,6461,6343,6080],"ability_uses":null,"account_id":175864981,"actions":null,"additional_units":null,"assists":0,"backpack_0":0,"backpack_1":0,"backpack_2":182,"buyback_log":null,"camps_stacked":null,"connection_log":null,"creeps_stacked":null,"damage":null,"damage_inflictor":null,"damage_inflictor_received":null,"damage_taken":null,"damage_targets":null,"deaths":0,"denies":13,"dn_t":null,"firstblood_claimed":null,"gold":3072,"gold_per_min":470,"gold_reasons":null,"gold_spent":13320,"gold_t":null,"hero_damage":11769,"hero_healing":0,"hero_hits":null,"hero_id":120,"item_0":75,"item_1":63,"item_2":90,"item_3":41,"item_4":166,"item_5":100,"item_uses":null,"kill_streaks":null,"killed":null,"killed_by":null,"kills":1,"kills_log":null,"lane_pos":null,"last_hits":305,"leaver_status":0,"level":24,"lh_t":null,"life_state":null,"max_hero_hit":null,"multi_kills":null,"obs":null,"obs_left_log":null,"obs_log":null,"obs_placed":null,"party_id":0,"party_size":1,"performance_others":null,"permanent_buffs":[{"permanent_buff":6,"stack_count":3}],"pings":null,"pred_vict":null,"purchase":null,"purchase_log":null,"randomed":null,"repicked":null,"roshans_killed":null,"rune_pickups":null,"runes":null,"runes_log":null,"sen":null,"sen_left_log":null,"sen_log":null,"sen_placed":null,"stuns":null,"teamfight_participation":null,"times":null,"tower_damage":390,"towers_killed":null,"xp_per_min":808,"xp_reasons":null,"xp_t":null,"personaname":"Belavia","name":null,"last_login":null,"radiant_win":true,"start_time":1562417131,"duration":2014,"cluster":136,"lobby_type":8,"game_mode":21,"is_contributor":false,"patch":41,"region":3,"isRadiant":true,"win":1,"lose":0,"total_gold":15776,"total_xp":27121,"kills_per_min":0.029791459781529292,"kda":1,"abandons":0,"rank_tier":44,"cosmetics":[],"benchmarks":{"gold_per_min":{"raw":470,"pct":0.48434085943190097},"xp_per_min":{"raw":808,"pct":0.9366351056081573},"kills_per_min":{"raw":0.029791459781529295,"pct":0.04515659140568099},"last_hits_per_min":{"raw":9.086395233366435,"pct":0.9715950473415877},"hero_damage_per_min":{"raw":350.6156901688183,"pct":0.11944646758922069},"hero_healing_per_min":{"raw":0,"pct":0.5651857246904588},"tower_damage":{"raw":390,"pct":0.3466860888565186},"stuns_per_min":{"raw":0,"pct":0.022578295702840496},"lhten":{}}},{"match_id":4887481193,"player_slot":1,"ability_targets":null,"ability_upgrades_arr":null,"ability_uses":null,"account_id":null,"actions":null,"additional_units":null,"assists":null,"backpack_0":null,"backpack_1":null,"backpack_2":null,"buyback_log":null,"camps_stacked":null,"connection_log":null,"creeps_stacked":null,"damage":null,"damage_inflictor":null,"damage_inflictor_received":null,"damage_taken":null,"damage_targets":null,"deaths":null,"denies":null,"dn_t":null,"firstblood_claimed":null,"gold":null,"gold_per_min":null,"gold_reasons":null,"gold_spent":null,"gold_t":null,"hero_damage":null,"hero_healing":null,"hero_hits":null,"hero_id":null,"item_0":null,"item_1":null,"item_2":null,"item_3":null,"item_4":null,"item_5":null,"item_uses":null,"kill_streaks":null,"killed":null,"killed_by":null,"kills":null,"kills_log":null,"lane_pos":null,"last_hits":null,"leaver_status":null,"level":null,"lh_t":null,"life_state":null,"max_hero_hit":null,"multi_kills":null,"obs":null,"obs_left_log":null,"obs_log":null,"obs_placed":null,"party_id":1,"party_size":1,"performance_others":null,"permanent_buffs":[{"permanent_buff":6,"stack_count":4}],"pings":null,"pred_vict":null,"purchase":null,"purchase_log":null,"randomed":null,"repicked":null,"roshans_killed":null,"rune_pickups":null,"runes":null,"runes_log":null,"sen":null,"sen_left_log":null,"sen_log":null,"sen_placed":null,"stuns":null,"teamfight_participation":null,"times":null,"tower_damage":null,"towers_killed":null,"xp_per_min":null,"xp_reasons":null,"xp_t":null,"radiant_win":true,"start_time":1562417131,"duration":2014,"cluster":136,"lobby_type":8,"game_mode":21,"is_contributor":false,"patch":41,"region":3,"isRadiant":true,"win":1,"lose":0,"kda":0,"abandons":0,"rank_tier":null,"cosmetics":[],"benchmarks":{"gold_per_min":{},"xp_per_min":{},"kills_per_min":{"raw":0,"pct":null},"last_hits_per_min":{"raw":0,"pct":null},"hero_damage_per_min":{"raw":0,"pct":null},"hero_healing_per_min":{"raw":0,"pct":null},"tower_damage":{},"stuns_per_min":{"raw":0,"pct":null},"lhten":{}}},{"match_id":4887481193,"player_slot":128,"ability_targets":null,"ability_upgrades_arr":[5603,5604,5603,5605,5605,5606,5605,5605,5603,6009,5603,5606,5604,5604,6176,5604,5606,5989],"ability_uses":null,"account_id":1015515338,"actions":null,"additional_units":null,"assists":0,"backpack_0":0,"backpack_1":0,"backpack_2":0,"buyback_log":null,"camps_stacked":null,"connection_log":null,"creeps_stacked":null,"damage":null,"damage_inflictor":null,"damage_inflictor_received":null,"damage_taken":null,"damage_targets":null,"deaths":1,"denies":25,"dn_t":null,"firstblood_claimed":null,"gold":30,"gold_per_min":401,"gold_reasons":null,"gold_spent":14270,"gold_t":null,"hero_damage":18939,"hero_healing":0,"hero_hits":null,"hero_id":106,"item_0":127,"item_1":190,"item_2":98,"item_3":0,"item_4":0,"item_5":50,"item_uses":null,"kill_streaks":null,"killed":null,"killed_by":null,"kills":0,"kills_log":null,"lane_pos":null,"last_hits":234,"leaver_status":0,"level":22,"lh_t":null,"life_state":null,"max_hero_hit":null,"multi_kills":null,"obs":null,"obs_left_log":null,"obs_log":null,"obs_placed":null,"party_id":null,"party_size":null,"performance_others":null,"permanent_buffs":null,"pings":null,"pred_vict":null,"purchase":null,"purchase_log":null,"randomed":null,"repicked":null,"roshans_killed":null,"rune_pickups":null,"runes":null,"runes_log":null,"sen":null,"sen_left_log":null,"sen_log":null,"sen_placed":null,"stuns":null,"teamfight_participation":null,"times":null,"tower_damage":514,"towers_killed":null,"xp_per_min":657,"xp_reasons":null,"xp_t":null,"personaname":null,"name":null,"last_login":null,"radiant_win":true,"start_time":1562417131,"duration":2014,"cluster":136,"lobby_type":8,"game_mode":21,"is_contributor":false,"patch":41,"region":3,"isRadiant":false,"win":0,"lose":1,"total_gold":13460,"total_xp":22053,"kda":0,"abandons":0,"rank_tier":null,"cosmetics":[],"benchmarks":{"gold_per_min":{"raw":401,"pct":0.16133584195672623},"xp_per_min":{"raw":657,"pct":0.43979303857008467},"kills_per_min":{"raw":0,"pct":0.017873941674506115},"last_hits_per_min":{"raw":6.971201588877855,"pct":0.8043273753527752},"hero_damage_per_min":{"raw":564.2204568023833,"pct":0.16745061147695203},"hero_healing_per_min":{"raw":0,"pct":0.7370649106302917},"tower_damage":{"raw":514,"pct":0.3085606773283161},"stuns_per_min":{"raw":0,"pct":0.0070555032925682035},"lhten":{}}}],"patch":41,"region":3,"replay_url":"http://replay136.valve.net/570/4887481193_1903585295.dem.bz2"}