{"match_id":4887480404,"barracks_status_dire":63,"barracks_status_radiant":48,"chat":null,"cluster":223,"cosmetics":null,"dire_score":38,"dire_team_id":null,"draft_timings":null,"duration":1586,"engine":1,"first_blood_time":81,"game_mode":19,"human_players":10,"leagueid":0,"lobby_type":12,"match_seq_num":4102608395,"negative_votes":0,"objectives":null,"picks_bans":null,"positive_votes":0,"radiant_gold_adv":null,"radiant_score":18,"radiant_team_id":null,"radiant_win":false,"radiant_xp_adv":null,"skill":null,"start_time":1562417095,"teamfights":null,"tower_status_dire":1975,"tower_status_radiant":384,"version":null,"players":[{"match_id":4887480404,"player_slot":0,"ability_targets":null,"ability_upgrades_arr":[5224,5222,5224,5222,5224,5225,5222,5222,5224,5906,5223,5225,5223,5223,6141,5223],"ability_uses":null,"account_id":204281370,"actions":null,"additional_units":null,"assists":3,"backpack_0":0,"backpack_1":0,"backpack_2":0,"buyback_log":null,"camps_stacked":null,"connection_log":null,"creeps_stacked":null,"damage":null,"damage_inflictor":null,"damage_inflictor_received":null,"damage_taken":null,"damage_targets":null,"deaths":6,"denies":9,"dn_t":null,"firstblood_claimed":null,"gold":570,"gold_per_min":433,"gold_reasons":null,"gold_spent":9640,"gold_t":null,"hero_damage":10738,"hero_healing":0,"hero_hits":null,"hero_id":48,"item_0":63,"item_1":16,"item_2":75,"item_3":75,"item_4":108,"item_5":170,"item_uses":null,"kill_streaks":null,"killed":null,"killed_by":null,"kills":7,"kills_log":null,"lane_pos":null,"last_hits":108,"leaver_status":0,"level":17,"lh_t":null,"life_state":null,"max_hero_hit":null,"multi_kills":null,"obs":null,"obs_left_log":null,"obs_log":null,"obs_placed":null,"party_id":null,"party_size":null,"performance_others":null,"permanent_buffs":null,"pings":null,"pred_vict":null,"purchase":null,"purchase_log":null,"randomed":null,"repicked":null,"roshans_killed":null,"rune_pickups":null,"runes":null,"runes_log":null,"sen":null,"sen_left_log":null,"sen_log":null,"sen_placed":null,"stuns":null,"teamfight_participation":null,"times":null,"tower_damage":805,"towers_killed":null,"xp_per_min":498,"xp_reasons":null,"xp_t":null,"personaname":"0.0","name":null,"last_login":null,"radiant_win":false,"start_time":1562417095,"duration":1586,"cluster":223,"lobby_type":12,"game_mode":19,"is_contributor":false,"patch":41,"region":18,"isRadiant":true,"win":0,"lose":1,"total_gold":11445,"total_xp":13163,"kills_per_min":0.2648171500630517,"kda":1,"abandons":0,"rank_tier":57,"cosmetics":[],"benchmarks":{"gold_per_min":{"raw":433,"pct":0.23143164693218515},"xp_per_min":{"raw":498,"pct":0.19590958019375673},"kills_per_min":{"raw":0.26481715006305173,"pct":0.790096878363832},"last_hits_per_min":{"raw":4.085750315258513,"pct":0.1054897739504844},"hero_damage_per_min":{"raw":406.2295081967213,"pct":0.21420882669537136},"hero_healing_per_min":{"raw":0,"pct":0.9601722282023681},"tower_damage":{"raw":805,"pct":0.22066738428417654},"stuns_per_min":{"raw":0,"pct":0.007534983853606028},"lhten":{}}},{"match_id":4887480404,"player_slot":1,"ability_targets":null,"ability_upgrades_arr":[5102,5103,5103,5104,5102,5105,5103,5102,5959,5102,5103,5105,5104,5104,6409,5104],"ability_uses":null,"account_id":149934985,"actions":null,"additional_units":null,"assists":7,"backpack_0":0,"backpack_1":0,"backpack_2":0,"buyback_log":null,"camps_stacked":null,"connection_log":null,"creeps_stacked":null,"damage":null,"damage_inflictor":null,"damage_inflictor_received":null,"damage_taken":null,"damage_targets":null,"deaths":7,"denies":9,"dn_t":null,"firstblood_claimed":null,"gold":360,"gold_per_min":323,"gold_reasons":null,"gold_spent":8675,"gold_t":null,"hero_damage":10651,"hero_healing":480,"hero_hits":null,"hero_id":16,"item_0":242,"item_1":1,"item_2":0,"item_3":92,"item_4":29,"item_5":0,"item_uses":null,"kill_streaks":null,"killed":null,"killed_by":null,"kills":2,"kills_log":null,"lane_pos":null,"last_hits":60,"leaver_status":0,"level":16,"lh_t":null,"life_state":null,"max_hero_hit":null,"multi_kills":null,"obs":null,"obs_left_log":null,"obs_log":null,"obs_placed":null,"party_id":null,"party_size":null,"performance_others":null,"permanent_buffs":null,"pings":null,"pred_vict":null,"purchase":null,"purchase_log":null,"randomed":null,"repicked":null,"roshans_killed":null,"rune_pickups":null,"runes":null,"runes_log":null,"sen":null,"sen_left_log":null,"sen_log":null,"sen_placed":null,"stuns":null,"teamfight_participation":null,"times":null,"tower_damage":22,"towers_killed":null,"xp_per_min":450,"xp_reasons":null,"xp_t":null,"personaname":"","name":null,"last_login":null,"radiant_win":false,"start_time":1562417095,"duration":1586,"cluster":223,"lobby_type":12,"game_mode":19,"is_contributor":false,"patch":41,"region":18,"isRadiant":true,"win":0,"lose":1,"total_gold":8537,"total_xp":11895,"kills_per_min":0.07566204287515763,"kda":1,"abandons":0,"rank_tier":null,"cosmetics":[],"benchmarks":{"gold_per_min":{"raw":323,"pct":0.16729464958553128},"xp_per_min":{"raw":450,"pct":0.23813112283345894},"kills_per_min":{"raw":0.07566204287515763,"pct":0.26827430293896004},"last_hits_per_min":{"raw":2.269861286254729,"pct":0.10851544837980406},"hero_damage_per_min":{"raw":402.93820933165193,"pct":0.19517709118311982},"hero_healing_per_min":{"raw":18.15889029003783,"pct":0.8718914845516202},"tower_damage":{"raw":22,"pct":0.18010550113036924},"stuns_per_min":{"raw":0,"pct":0.0015071590052750565},"lhten":{}}},{"match_id":4887480404,"player_slot":2,"ability_targets":null,"ability_upgrades_arr":[5127,5128,5126,5128,5127,5128,5129,5128,5126,5127,5127],"ability_uses":null,"account_id":151788472,"actions":null,"additional_units":null,"assists":3,"backpack_0":0,"backpack_1":0,"backpack_2":0,"buyback_log":null,"camps_stacked":null,"connection_log":null,"creeps_stacked":null,"damage":null,"damage_inflictor":null,"damage_inflictor_received":null,"damage_taken":null,"damage_targets":null,"deaths":7,"denies":2,"dn_t":null,"firstblood_claimed":null,"gold":374,"gold_per_min":254,"gold_reasons":null,"gold_spent":6255,"gold_t":null,"hero_damage":9051,"hero_healing":0,"hero_hits":null,"hero_id":5,"item_0":254,"item_1":214,"item_2":261,"item_3":261,"item_4":23,"item_5":43,"item_uses":null,"kill_streaks":null,"killed":null,"killed_by":null,"kills":2,"kills_log":null,"lane_pos":null,"last_hits":27,"leaver_status":0,"level":12,"lh_t":null,"life_state":null,"max_hero_hit":null,"multi_kills":null,"obs":null,"obs_left_log":null,"obs_log":null,"obs_placed":null,"party_id":null,"party_size":null,"performance_others":null,"permanent_buffs":null,"pings":null,"pred_vict":null,"purchase":null,"purchase_log":null,"randomed":null,"repicked":null,"roshans_killed":null,"rune_pickups":null,"runes":null,"runes_log":null,"sen":null,"sen_left_log":null,"sen_log":null,"sen_placed":null,"stuns":null,"teamfight_participation":null,"times":null,"tower_damage":359,"towers_killed":null,"xp_per_min":266,"xp_reasons":null,"xp_t":null,"personaname":"","name":null,"last_login":null,"radiant_win":false,"start_time":1562417095,"duration":1586,"cluster":223,"lobby_type":12,"game_mode":19,"is_contributor":false,"patch":41,"region":18,"isRadiant":true,"win":0,"lose":1,"total_gold":6714,"total_xp":7031,"kills_per_min":0.07566204287515763,"kda":0,"abandons":0,"rank_tier":null,"cosmetics":[],"benchmarks":{"gold_per_min":{"raw":254,"pct":0.14498567335243553},"xp_per_min":{"raw":266,"pct":0.07106017191977078},"kills_per_min":{"raw":0.07566204287515763,"pct":0.37593123209169055},"last_hits_per_min":{"raw":1.0214375788146282,"pct":0.2297994269340974},"hero_damage_per_min":{"raw":342.40857503152586,"pct":0.3816618911174785},"hero_healing_per_min":{"raw":0,"pct":0.8097421203438395},"tower_damage":{"raw":359,"pct":0.49283667621776506},"stuns_per_min":{"raw":0,"pct":0.004584527220630372},"lhten":{}}},{"match_id":4887480404,"player_slot":3,"ability_targets":null,"ability_upgrades_arr":[5021,5019,5021,5019,5021,5022,5021,5632,5019,5921,5632,5022,5019,5632,6029],"ability_uses":null,"account_id":71703051,"actions":null,"additional_units":null,"assists":5,"backpack_0":0,"backpack_1":0,"backpack_2":0,"buyback_log":null,"camps_stacked":null,"connection_log":null,"creeps_stacked":null,"damage":null,"damage_inflictor":null,"damage_inflictor_received":null,"damage_taken":null,"damage_targets":null,"deaths":6,"denies":6,"dn_t":null,"firstblood_claimed":null,"gold":368,"gold_per_min":382,"gold_reasons":null,"gold_spent":9860,"gold_t":null,"hero_damage":6683,"hero_healing":0,"hero_hits":null,"hero_id":6,"item_0":152,"item_1":75,"item_2":236,"item_3":75,"item_4":51,"item_5":63,"item_uses":null,"kill_streaks":null,"killed":null,"killed_by":null,"kills":4,"kills_log":null,"lane_pos":null,"last_hits":104,"leaver_status":0,"level":15,"lh_t":null,"life_state":null,"max_hero_hit":null,"multi_kills":null,"obs":null,"obs_left_log":null,"obs_log":null,"obs_placed":null,"party_id":null,"party_size":null,"performance_others":null,"permanent_buffs":null,"pings":null,"pred_vict":null,"purchase":null,"purchase_log":null,"randomed":null,"repicked":null,"roshans_killed":null,"rune_pickups":null,"runes":null,"runes_log":null,"sen":null,"sen_left_log":null,"sen_log":null,"sen_placed":null,"stuns":null,"teamfight_participation":null,"times":null,"tower_damage":1037,"towers_killed":null,"xp_per_min":440,"xp_reasons":null,"xp_t":null,"personaname":"Gneiss_Knight","name":null,"last_login":null,"radiant_win":false,"start_time":1562417095,"duration":1586,"cluster":223,"lobby_type":12,"game_mode":19,"is_contributor":false,"patch":41,"region":18,"isRadiant":true,"win":0,"lose":1,"total_gold":10097,"total_xp":11630,"kills_per_min":0.15132408575031525,"kda":1,"abandons":0,"rank_tier":72,"cosmetics":[],"benchmarks":{"gold_per_min":{"raw":382,"pct":0.1865234375},"xp_per_min":{"raw":440,"pct":0.166015625},"kills_per_min":{"raw":0.15132408575031525,"pct":0.4892578125},"last_hits_per_min":{"raw":3.934426229508197,"pct":0.1162109375},"hero_damage_per_min":{"raw":252.82471626733923,"pct":0.1728515625},"hero_healing_per_min":{"raw":0,"pct":0.9765625},"tower_damage":{"raw":1037,"pct":0.28125},"stuns_per_min":{"raw":0,"pct":0.9755859375},"lhten":{}}},{"match_id":4887480404,"player_slot":4,"ability_targets":null,"ability_upgrades_arr":[5044,5045,5044,5046,5044,5047,5044,5045,5045,5968,5045,5047,5046],"ability_uses":null,"account_id":123596006,"actions":null,"additional_units":null,"assists":7,"backpack_0":0,"backpack_1":0,"backpack_2":0,"buyback_log":null,"camps_stacked":null,"connection_log":null,"creeps_stacked":null,"damage":null,"damage_inflictor":null,"damage_inflictor_received":null,"damage_taken":null,"damage_targets":null,"deaths":12,"denies":1,"dn_t":null,"firstblood_claimed":null,"gold":847,"gold_per_min":261,"gold_reasons":null,"gold_spent":5650,"gold_t":null,"hero_damage":6593,"hero_healing":0,"hero_hits":null,"hero_id":26,"item_0":214,"item_1":261,"item_2":261,"item_3":41,"item_4":1,"item_5":0,"item_uses":null,"kill_streaks":null,"killed":null,"killed_by":null,"kills":3,"kills_log":null,"lane_pos":null,"last_hits":26,"leaver_status":0,"level":13,"lh_t":null,"life_state":null,"max_hero_hit":null,"multi_kills":null,"obs":null,"obs_left_log":null,"obs_log":null,"obs_placed":null,"party_id":null,"party_size":null,"performance_others":null,"permanent_buffs":null,"pings":null,"pred_vict":null,"purchase":null,"purchase_log":null,"randomed":null,"repicked":null,"roshans_killed":null,"rune_pickups":null,"runes":null,"runes_log":null,"sen":null,"sen_left_log":null,"sen_log":null,"sen_placed":null,"stuns":null,"teamfight_participation":null,"times":null,"tower_damage":66,"towers_killed":null,"xp_per_min":310,"xp_reasons":null,"xp_t":null,"personaname":"","name":null,"last_login":null,"radiant_win":false,"start_time":1562417095,"duration":1586,"cluster":223,"lobby_type":12,"game_mode":19,"is_contributor":false,"patch":41,"region":18,"isRadiant":true,"win":0,"lose":1,"total_gold":6899,"total_xp":8194,"kills_per_min":0.11349306431273644,"kda":0,"abandons":0,"rank_tier":46,"cosmetics":[],"benchmarks":{"gold_per_min":{"raw":261,"pct":0.23684210526315788},"xp_per_min":{"raw":310,"pct":0.13283208020050125},"kills_per_min":{"raw":0.11349306431273644,"pct":0.42794486215538846},"last_hits_per_min":{"raw":0.9836065573770493,"pct":0.474937343358396},"hero_damage_per_min":{"raw":249.41992433795713,"pct":0.34210526315789475},"hero_healing_per_min":{"raw":0,"pct":0.8204887218045113},"tower_damage":{"raw":66,"pct":0.3217418546365915},"stuns_per_min":{"raw":0,"pct":0.0006265664160401002},"lhten":{}}},{"match_id":4887480404,"player_slot":128,"ability_targets":null,"ability_upgrades_arr":[5249,5250,5250,5251,5250,5252,5249,5250,5249,5906,5249,5252,5251,5251,5919,5251,5252],"ability_uses":null,"account_id":null,"actions":null,"additional_units":null,"assists":8,"backpack_0":48,"backpack_1":0,"backpack_2":0,"buyback_log":null,"camps_stacked":null,"connection_log":null,"creeps_stacked":null,"damage":null,"damage_inflictor":null,"damage_inflictor_received":null,"damage_taken":null,"damage_targets":null,"deaths":0,"denies":18,"dn_t":null,"firstblood_claimed":null,"gold":23787,"gold_per_min":415,"gold_reasons":null,"gold_spent":37795,"gold_t":null,"hero_damage":10184,"hero_healing":505,"hero_hits":null,"hero_id":54,"item_0":50,"item_1":225,"item_2":147,"item_3":112,"item_4":208,"item_5":250,"item_uses":null,"kill_streaks":null,"killed":null,"killed_by":null,"kills":5,"kills_log":null,"lane_pos":null,"last_hits":89,"leaver_status":0,"level":20,"lh_t":null,"life_state":null,"max_hero_hit":null,"multi_kills":null,"obs":null,"obs_left_log":null,"obs_log":null,"obs_placed":null,"party_id":null,"party_size":null,"performance_others":null,"permanent_buffs":null,"pings":null,"pred_vict":null,"purchase":null,"purchase_log":null,"randomed":null,"repicked":null,"roshans_killed":null,"rune_pickups":null,"runes":null,"runes_log":null,"sen":null,"sen_left_log":null,"sen_log":null,"sen_placed":null,"stuns":null,"teamfight_participation":null,"times":null,"tower_damage":3653,"towers_killed":null,"xp_per_min":690,"xp_reasons":null,"xp_t":null,"radiant_win":false,"start_time":1562417095,"duration":1586,"cluster":223,"lobby_type":12,"game_mode":19,"is_contributor":false,"patch":41,"region":18,"isRadiant":false,"win":1,"lose":0,"total_gold":10969,"total_xp":18239,"kills_per_min":0.18915510718789408,"kda":13,"abandons":0,"rank_tier":null,"cosmetics":[],"benchmarks":{"gold_per_min":{"raw":415,"pct":0.17034700315457413},"xp_per_min":{"raw":690,"pct":0.5362776025236593},"kills_per_min":{"raw":0.18915510718789408,"pct":0.5118296529968455},"last_hits_per_min":{"raw":3.3669609079445144,"pct":0.051261829652996846},"hero_damage_per_min":{"raw":385.27112232030265,"pct":0.23659305993690852},"hero_healing_per_min":{"raw":19.1046658259773,"pct":0.16167192429022081},"tower_damage":{"raw":3653,"pct":0.5394321766561514},"stuns_per_min":{"raw":0,"pct":0.5197160883280757},"lhten":{}}},{"match_id":4887480404,"player_slot":129,"ability_targets":null,"ability_upgrades_arr":[5132,5131,5130,5131,5131,5133,5131,5130,5130,6160,5132,5133,5132,5132,6562,5130],"ability_uses":null,"account_id":194565153,"actions":null,"additional_units":null,"assists":13,"backpack_0":0,"backpack_1":0,"backpack_2":0,"buyback_log":null,"camps_stacked":null,"connection_log":null,"creeps_stacked":null,"damage":null,"damage_inflictor":null,"damage_inflictor_received":null,"damage_taken":null,"damage_targets":null,"deaths":7,"denies":17,"dn_t":null,"firstblood_claimed":null,"gold":2656,"gold_per_min":362,"gold_reasons":null,"gold_spent":6930,"gold_t":null,"hero_damage":8410,"hero_healing":0,"hero_hits":null,"hero_id":21,"item_0":0,"item_1":77,"item_2":36,"item_3":50,"item_4":166,"item_5":77,"item_uses":null,"kill_streaks":null,"killed":null,"killed_by":null,"kills":2,"kills_log":null,"lane_pos":null,"last_hits":66,"leaver_status":0,"level":16,"lh_t":null,"life_state":null,"max_hero_hit":null,"multi_kills":null,"obs":null,"obs_left_log":null,"obs_log":null,"obs_placed":null,"party_id":null,"party_size":null,"performance_others":null,"permanent_buffs":null,"pings":null,"pred_vict":null,"purchase":null,"purchase_log":null,"randomed":null,"repicked":null,"roshans_killed":null,"rune_pickups":null,"runes":null,"runes_log":null,"sen":null,"sen_left_log":null,"sen_log":null,"sen_placed":null,"stuns":null,"teamfight_participation":null,"times":null,"tower_damage":3216,"towers_killed":null,"xp_per_min":479,"xp_reasons":null,"xp_t":null,"personaname":"","name":null,"last_login":null,"radiant_win":false,"start_time":1562417095,"duration":1586,"cluster":223,"lobby_type":12,"game_mode":19,"is_contributor":false,"patch":41,"region":18,"isRadiant":false,"win":1,"lose":0,"total_gold":9568,"total_xp":12661,"kills_per_min":0.07566204287515763,"kda":1,"abandons":0,"rank_tier":54,"cosmetics":[],"benchmarks":{"gold_per_min":{"raw":362,"pct":0.1923318667504714},"xp_per_min":{"raw":479,"pct":0.2203016970458831},"kills_per_min":{"raw":0.07566204287515763,"pct":0.0842237586423633},"last_hits_per_min":{"raw":2.496847414880202,"pct":0.11376492771841609},"hero_damage_per_min":{"raw":318.1588902900378,"pct":0.05782526712759271},"hero_healing_per_min":{"raw":0,"pct":0.8972344437460716},"tower_damage":{"raw":3216,"pct":0.6319924575738529},"stuns_per_min":{"raw":0,"pct":0.0056568196103079825},"lhten":{}}},{"match_id":4887480404,"player_slot":130,"ability_targets":null,"ability_upgrades_arr":[5150,5151,5150,5151,5150,5151,5153,5152,5152,5152,5152,5153,5151,6003,5957,5150,5153],"ability_uses":null,"account_id":145344507,"actions":null,"additional_units":null,"assists":14,"backpack_0":0,"backpack_1":0,"backpack_2":0,"buyback_log":null,"camps_stacked":null,"connection_log":null,"creeps_stacked":null,"damage":null,"damage_inflictor":null,"damage_inflictor_received":null,"damage_taken":null,"damage_targets":null,"deaths":5,"denies":14,"dn_t":null,"firstblood_claimed":null,"gold":179,"gold_per_min":562,"gold_reasons":null,"gold_spent":14525,"gold_t":null,"hero_damage":24591,"hero_healing":0,"hero_hits":null,"hero_id":34,"item_0":1,"item_1":77,"item_2":41,"item_3":204,"item_4":178,"item_5":48,"item_uses":null,"kill_streaks":null,"killed":null,"killed_by":null,"kills":14,"kills_log":null,"lane_pos":null,"last_hits":111,"leaver_status":0,"level":18,"lh_t":null,"life_state":null,"max_hero_hit":null,"multi_kills":null,"obs":null,"obs_left_log":null,"obs_log":null,"obs_placed":null,"party_id":null,"party_size":null,"performance_others":null,"permanent_buffs":null,"pings":null,"pred_vict":null,"purchase":null,"purchase_log":null,"randomed":null,"repicked":null,"roshans_killed":null,"rune_pickups":null,"runes":null,"runes_log":null,"sen":null,"sen_left_log":null,"sen_log":null,"sen_placed":null,"stuns":null,"teamfight_participation":null,"times":null,"tower_damage":1549,"towers_killed":null,"xp_per_min":594,"xp_reasons":null,"xp_t":null,"personaname":"","name":null,"last_login":null,"radiant_win":false,"start_time":1562417095,"duration":1586,"cluster":223,"lobby_type":12,"game_mode":19,"is_contributor":false,"patch":41,"region":18,"isRadiant":false,"win":1,"lose":0,"total_gold":14855,"total_xp":15701,"kills_per_min":0.5296343001261034,"kda":4,"abandons":0,"rank_tier":66,"cosmetics":[],"benchmarks":{"gold_per_min":{"raw":562,"pct":0.36603375527426163},"xp_per_min":{"raw":594,"pct":0.2890295358649789},"kills_per_min":{"raw":0.5296343001261035,"pct":0.9419831223628692},"last_hits_per_min":{"raw":4.199243379571248,"pct":0.10232067510548523},"hero_damage_per_min":{"raw":930.3026481715006,"pct":0.3449367088607595},"hero_healing_per_min":{"raw":0,"pct":0.6487341772151899},"tower_damage":{"raw":1549,"pct":0.9873417721518988},"stuns_per_min":{"raw":0,"pct":0.439873417721519},"lhten":{}}},{"match_id":4887480404,"player_slot":131,"ability_targets":null,"ability_upgrades_arr":[5075,5076,5075,5076,5075,5077,5075,5076,5076,6317,5074,5077,5074,5074,6560],"ability_uses":null,"account_id":193349151,"actions":null,"additional_units":null,"assists":7,"backpack_0":0,"backpack_1":0,"backpack_2":0,"buyback_log":null,"camps_stacked":null,"connection_log":null,"creeps_stacked":null,"damage":null,"damage_inflictor":null,"damage_inflictor_received":null,"damage_taken":null,"damage_targets":null,"deaths":4,"denies":3,"dn_t":null,"firstblood_claimed":null,"gold":2924,"gold_per_min":311,"gold_reasons":null,"gold_spent":5475,"gold_t":null,"hero_damage":6528,"hero_healing":57,"hero_hits":null,"hero_id":14,"item_0":92,"item_1":131,"item_2":36,"item_3":214,"item_4":0,"item_5":182,"item_uses":null,"kill_streaks":null,"killed":null,"killed_by":null,"kills":5,"kills_log":null,"lane_pos":null,"last_hits":30,"leaver_status":0,"level":15,"lh_t":null,"life_state":null,"max_hero_hit":null,"multi_kills":null,"obs":null,"obs_left_log":null,"obs_log":null,"obs_placed":null,"party_id":null,"party_size":null,"performance_others":null,"permanent_buffs":null,"pings":null,"pred_vict":null,"purchase":null,"purchase_log":null,"randomed":null,"repicked":null,"roshans_killed":null,"rune_pickups":null,"runes":null,"runes_log":null,"sen":null,"sen_left_log":null,"sen_log":null,"sen_placed":null,"stuns":null,"teamfight_participation":null,"times":null,"tower_damage":277,"towers_killed":null,"xp_per_min":428,"xp_reasons":null,"xp_t":null,"personaname":"","name":null,"last_login":null,"radiant_win":false,"start_time":1562417095,"duration":1586,"cluster":223,"lobby_type":12,"game_mode":19,"is_contributor":false,"patch":41,"region":18,"isRadiant":false,"win":1,"lose":0,"total_gold":8220,"total_xp":11313,"kills_per_min":0.18915510718789408,"kda":2,"abandons":0,"rank_tier":47,"cosmetics":[],"benchmarks":{"gold_per_min":{"raw":311,"pct":0.31368921775898523},"xp_per_min":{"raw":428,"pct":0.266384778012685},"kills_per_min":{"raw":0.18915510718789408,"pct":0.61892177589852},"last_hits_per_min":{"raw":1.1349306431273645,"pct":0.23361522198731502},"hero_damage_per_min":{"raw":246.96090794451447,"pct":0.10438689217758985},"hero_healing_per_min":{"raw":2.1563682219419924,"pct":0.754492600422833},"tower_damage":{"raw":277,"pct":0.47330866807610994},"stuns_per_min":{"raw":0,"pct":0.0010570824524312897},"lhten":{}}},{"match_id":4887480404,"player_slot":132,"ability_targets":null,"ability_upgrades_arr":[5154,5156,5155,5155,5154,5157,5156,5154,5154,5960,5156,5157,5156,5155,6210,5155,5157],"ability_uses":null,"account_id":137480413,"actions":null,"additional_units":null,"assists":10,"backpack_0":0,"backpack_1":26,"backpack_2":0,"buyback_log":null,"camps_stacked":null,"connection_log":null,"creeps_stacked":null,"damage":null,"damage_inflictor":null,"damage_inflictor_received":null,"damage_taken":null,"damage_targets":null,"deaths":2,"denies":9,"dn_t":null,"firstblood_claimed":null,"gold":16058,"gold_per_min":645,"gold_reasons":null,"gold_spent":52045,"gold_t":null,"hero_damage":22726,"hero_healing":0,"hero_hits":null,"hero_id":35,"item_0":133,"item_1":63,"item_2":263,"item_3":158,"item_4":141,"item_5":135,"item_uses":null,"kill_streaks":null,"killed":null,"killed_by":null,"kills":12,"kills_log":null,"lane_pos":null,"last_hits":149,"leaver_status":0,"level":18,"lh_t":null,"life_state":null,"max_hero_hit":null,"multi_kills":null,"obs":null,"obs_left_log":null,"obs_log":null,"obs_placed":null,"party_id":null,"party_size":null,"performance_others":null,"permanent_buffs":null,"pings":null,"pred_vict":null,"purchase":null,"purchase_log":null,"randomed":null,"repicked":null,"roshans_killed":null,"rune_pickups":null,"runes":null,"runes_log":null,"sen":null,"sen_left_log":null,"sen_log":null,"sen_placed":null,"stuns":null,"teamfight_participation":null,"times":null,"tower_damage":14013,"towers_killed":null,"xp_per_min":544,"xp_reasons":null,"xp_t":null,"personaname":"Ysy","name":null,"last_login":null,"radiant_win":false,"start_time":1562417095,"duration":1586,"cluster":223,"lobby_type":12,"game_mode":19,"is_contributor":false,"patch":41,"region":18,"isRadiant":false,"win":1,"lose":0,"total_gold":17049,"total_xp":14379,"kills_per_min":0.45397225725094575,"kda":7,"abandons":0,"rank_tier":44,"cosmetics":[],"benchmarks":{"gold_per_min":{"raw":645,"pct":0.8373353989155693},"xp_per_min":{"raw":544,"pct":0.29047250193648333},"kills_per_min":{"raw":0.45397225725094575,"pct":0.930286599535244},"last_hits_per_min":{"raw":5.636822194199243,"pct":0.4051123160340821},"hero_damage_per_min":{"raw":859.7477931904161,"pct":0.6018590240123934},"hero_healing_per_min":{"raw":0,"pct":0.9713400464756003},"tower_damage":{"raw":14013,"pct":0.9922540666150271},"stuns_per_min":{"raw":0,"pct":0.030209140201394268},"lhten":{}}}],"patch":41,"region":18}